glyphsynth/__init__.py
glyphsynth/cli/export.py
glyphsynth/drawing/__init__.py
glyphsynth/drawing/_utils.py
glyphsynth/drawing/drawing.py
glyphsynth/drawing/export.py
glyphsynth/drawing/graphics/__init__.py
glyphsynth/drawing/graphics/_container.py
glyphsynth/drawing/graphics/_export.py
glyphsynth/drawing/graphics/_model.py
glyphsynth/drawing/graphics/elements/__init__.py
glyphsynth/drawing/graphics/elements/_factory.py
glyphsynth/drawing/graphics/elements/_mixins.py
glyphsynth/drawing/graphics/elements/base.py
glyphsynth/drawing/graphics/elements/containers.py
glyphsynth/drawing/graphics/elements/gradients.py
glyphsynth/drawing/graphics/elements/shapes.py
glyphsynth/drawing/graphics/properties.py
glyphsynth/glyph/__init__.py
glyphsynth/glyph/glyph.py
glyphsynth/glyph/letters.py
glyphsynth/lib/__init__.py
glyphsynth/lib/alphabets/latin/runic.py
glyphsynth/lib/alphabets/latin/traditional.py
glyphsynth/lib/array.py
glyphsynth/lib/logo.py
glyphsynth/lib/matrix.py
glyphsynth/lib/utils.py
glyphsynth/lib/variants.py
glyphsynth-0.8.1.dist-info/LICENSE
glyphsynth-0.8.1.dist-info/METADATA
glyphsynth-0.8.1.dist-info/WHEEL
glyphsynth-0.8.1.dist-info/entry_points.txt
glyphsynth-0.8.1.dist-info/RECORD
