Metadata-Version: 2.3
Name: glyphsynth
Version: 0.8.1
Summary: Pythonic vector graphics synthesis toolkit
Author: mm21
Author-email: mm21.dev@gmail.com
Requires-Python: >=3.12,<4.0
Classifier: Programming Language :: Python :: Implementation :: CPython
Classifier: Operating System :: OS Independent
Classifier: Typing :: Typed
Classifier: Topic :: Software Development :: Libraries :: Python Modules
Classifier: Development Status :: 3 - Alpha
Classifier: Natural Language :: English
Classifier: License :: OSI Approved :: MIT License
Classifier: Programming Language :: Python :: 3
Classifier: Programming Language :: Python :: 3.12
Classifier: Programming Language :: Python :: 3.13
Requires-Dist: pydantic (>=2.5.3,<3.0.0)
Requires-Dist: pyrollup (>=0.1.0,<0.2.0)
Requires-Dist: rich (>=13.9.3,<14.0.0)
Requires-Dist: svgwrite (>=1.4.3,<2.0.0)
Requires-Dist: typer[all] (>=0.15.0,<0.16.0)
Project-URL: Homepage, https://github.com/mm21/glyphsynth
